{
  "$schema": "../../schemas/simple_table.json",
  "source": "third-party/exiftool/lib/Image/ExifTool/Olympus.pm",
  "description": "Olympus module lookup tables for camera types, lens types, and filters",
  "tables": [
    {
      "hash_name": "%olympusCameraTypes",
      "constant_name": "OLYMPUS_CAMERA_TYPES",
      "key_type": "String",
      "description": "Olympus camera type codes to camera names"
    },
    {
      "hash_name": "%olympusLensTypes",
      "constant_name": "OLYMPUS_LENS_TYPES",
      "key_type": "String",
      "description": "Olympus lens type codes to lens names"
    },
    {
      "hash_name": "%filters",
      "constant_name": "OLYMPUS_FILTERS",
      "key_type": "u8",
      "description": "Olympus art filter modes"
    }
  ]
}
