{
  "SourceFile": "third-party/exiftool/t/images/CanonRaw.cr2",
  "File:FileSize": 8724,
  "ExifTool:ExifToolVersion": 13.31,
  "File:FileName": "CanonRaw.cr2",
  "File:Directory": "third-party/exiftool/t/images",
  "File:FileModifyDate": "2025:06:30 12:33:09-07:00",
  "File:FileAccessDate": "2025:07:28 12:15:39-07:00",
  "File:FileInodeChangeDate": "2025:07:23 10:36:33-07:00",
  "File:FilePermissions": "-rw-rw-r--",
  "File:FileType": "CR2",
  "File:FileTypeExtension": "cr2",
  "File:MIMEType": "image/x-canon-cr2",
  "EXIF:ImageWidth": 1536,
  "EXIF:ImageHeight": 1024,
  "EXIF:Make": "Canon",
  "EXIF:Model": "Canon EOS 350D DIGITAL",
  "EXIF:Orientation": "Horizontal (normal)",
  "EXIF:ResolutionUnit": "inches",
  "EXIF:ModifyDate": "2005:08:03 18:59:18",
  "EXIF:ExposureTime": "1/15",
  "EXIF:FNumber": 8.0,
  "EXIF:ExposureProgram": "Aperture-priority AE",
  "EXIF:ISO": 400,
  "EXIF:DateTimeOriginal": "2005:08:03 18:59:18",
  "EXIF:CreateDate": "2005:08:03 18:59:18",
  "EXIF:ShutterSpeedValue": "1/15",
  "EXIF:ApertureValue": 8.0,
  "EXIF:MeteringMode": "Average",
  "EXIF:Flash": "Off, Did not fire",
  "EXIF:FocalLength": "55.0 mm",
  "MakerNotes:LensType": "n/a",
  "MakerNotes:FocalLength": "55 mm",
  "MakerNotes:FNumber": 8,
  "MakerNotes:ExposureTime": "1/16",
  "MakerNotes:FileNumber": "100-0024",
  "EXIF:ExifImageWidth": 3456,
  "EXIF:ExifImageHeight": 2304,
  "Composite:ISO": 400,
  "Composite:Lens": "18.0 - 55.0 mm",
  "Composite:Aperture": 8.0,
  "EXIF:PreviewImage": "(Binary data 26 bytes, use -b option to extract)",
  "Composite:ShutterSpeed": "1/15",
  "EXIF:ThumbnailImage": "(Binary data 28 bytes, use -b option to extract)",
  "Composite:ImageSize": "3456x2304",
  "Composite:LensID": "Unknown 18-55mm",
  "Composite:Megapixels": 8.0
}
